authhub_sdk/__init__.py
authhub_sdk/checker.py
authhub_sdk/client.py
authhub_sdk/decorators.py
authhub_sdk/exceptions.py
authhub_sdk/sso.py
authhub_sdk/verifier.py
authhub_sdk/middleware/__init__.py
authhub_sdk/middleware/fastapi.py
authhub_sdk/middleware/fastapi_sso.py
authhub_sdk/middleware/flask.py
authhub_sdk-0.3.0.dist-info/METADATA
authhub_sdk-0.3.0.dist-info/WHEEL
authhub_sdk-0.3.0.dist-info/RECORD
