Metadata-Version: 2.4
Name: authhub-sdk
Version: 0.3.0
Summary: AuthHub Python SDK - 统一权限平台SDK
Project-URL: Homepage, https://github.com/your-org/AuthHub
Project-URL: Documentation, https://docs.authhub.com
Project-URL: Repository, https://github.com/your-org/AuthHub/sdk/python
Author-email: AuthHub Team <sdk@authhub.com>
License: MIT
Classifier: Development Status :: 4 - Beta
Classifier: Intended Audience :: Developers
Classifier: License :: OSI Approved :: MIT License
Classifier: Programming Language :: Python :: 3
Classifier: Programming Language :: Python :: 3.11
Classifier: Programming Language :: Python :: 3.12
Requires-Python: >=3.11
Requires-Dist: cryptography>=41.0.7
Requires-Dist: fastapi>=0.121.2
Requires-Dist: loguru>=0.7.0
Requires-Dist: pyjwt[crypto]>=2.8.0
Requires-Dist: redis>=5.0.1
Requires-Dist: requests>=2.31.0
Requires-Dist: uvicorn>=0.38.0
Provides-Extra: dev
Requires-Dist: black>=23.12.0; extra == 'dev'
Requires-Dist: pytest-asyncio>=0.21.1; extra == 'dev'
Requires-Dist: pytest>=7.4.3; extra == 'dev'
Requires-Dist: ruff>=0.1.8; extra == 'dev'
Provides-Extra: django
Requires-Dist: django>=4.2.0; extra == 'django'
Provides-Extra: fastapi
Requires-Dist: fastapi>=0.104.0; extra == 'fastapi'
Provides-Extra: flask
Requires-Dist: flask>=3.0.0; extra == 'flask'
